{
    "1": {
        "write": {
            "avg": 0.11363148031563597,
            "std": 0.4544005662959113,
            "max": 2.518088674545288,
            "min": 0.02490694522857666,
            "conf": [
                0.1132800824437341,
                0.11398287818753784
            ]
        },
        "read": {
            "avg": 0.0277226448059082,
            "std": 0.0009077408112089174,
            "max": 0.02936546802520752,
            "min": 0.02490694522857666,
            "conf": [
                0.02737124693400633,
                0.02807404267781007
            ]
        }
    },
    "50": {
        "write": {
            "avg": 1.0740856957106755,
            "std": 0.5673075777615357,
            "max": 3.5604116058349615,
            "min": 0.6059438824653627,
            "conf": [
                0.9497090276695556,
                1.1984623637517955
            ]
        },
        "read": {
            "avg": 0.9940930701124256,
            "std": 0.3212932876686208,
            "max": 2.090795439243316,
            "min": 0.6059438824653627,
            "conf": [
                0.8697164020713057,
                1.1184697381535456
            ]
        }
    },
    "100": {
        "write": {
            "avg": 2.6103285999462518,
            "std": 1.1201437157880147,
            "max": 5.395095272302626,
            "min": 1.1474760394096375,
            "conf": [
                2.227527938924566,
                2.9931292609679376
            ]
        },
        "read": {
            "avg": 2.5126302417804456,
            "std": 0.9888613743915123,
            "max": 4.701641950845719,
            "min": 1.1474760394096375,
            "conf": [
                2.1298295807587597,
                2.8954309028021314
            ]
        }
    },
    "150": {
        "write": {
            "avg": 4.111736702206492,
            "std": 1.2608525470419756,
            "max": 6.41143907515208,
            "min": 1.498778650601705,
            "conf": [
                3.6420544420409686,
                4.581418962372015
            ]
        },
        "read": {
            "avg": 4.071667212261551,
            "std": 1.2132963513568218,
            "max": 6.41143907515208,
            "min": 1.498778650601705,
            "conf": [
                3.601984952096028,
                4.541349472427075
            ]
        }
    },
    "200": {
        "write": {
            "avg": 5.391939008889529,
            "std": 1.9304424951745873,
            "max": 9.208561927199368,
            "min": 2.376819275140763,
            "conf": [
                4.663569033664679,
                6.120308984114379
            ]
        },
        "read": {
            "avg": 5.324642526511489,
            "std": 1.8815456923298097,
            "max": 9.208561927199368,
            "min": 2.376819275140763,
            "conf": [
                4.596272551286639,
                6.053012501736339
            ]
        }
    },
    "250": {
        "write": {
            "avg": 6.879661885557503,
            "std": 2.2103791627954616,
            "max": 12.156148131752015,
            "min": 3.2686763609886174,
            "conf": [
                6.1129253879997565,
                7.64639838311525
            ]
        },
        "read": {
            "avg": 6.724784236602126,
            "std": 1.9806551659223386,
            "max": 10.61756499509811,
            "min": 3.2686763609886174,
            "conf": [
                5.958047739044379,
                7.491520734159873
            ]
        }
    }
}